crymon/__init__.py
crymon/_crymon.cp36-win_amd64.pyd
crymon/reconstruct.py
crymon-2017.12.14.dist-info/METADATA
crymon-2017.12.14.dist-info/RECORD
crymon-2017.12.14.dist-info/WHEEL
crymon-2017.12.14.dist-info/top_level.txt
