Metadata-Version: 2.1
Name: crymon
Version: 2017.12.14
Summary: Routines for crystallography with single crystals
Home-page: https://hg.3lp.cx/crymon
Author: Vadim Dyadkin
Author-email: dyadkin@gmail.com
License: GPLv3
Platform: UNKNOWN
Classifier: License :: OSI Approved :: GNU General Public License v3 (GPLv3)
Classifier: Programming Language :: Python
Classifier: Programming Language :: Python :: 3.6
Classifier: Programming Language :: Python :: Implementation :: CPython
Requires-Dist: cryio
Requires-Dist: numpy
